encryption.vhd
library ieee;
use ieee.std_logic_1164.all;
use ieee.numeric_std.all;

entity encryption is
    Port(
        dataIn: in std_logic_vector(7 downto 0); -- Data input (plaintext)
        keyIn: in std_logic_vector(7 downto 0); -- Key input
        dataOut: out std_logic_vector(7 downto 0); -- Data output (ciphertext)
        clk: in std_logic; -- Internal clock
        clr: in std_logic -- Clear
    );
end encryption;

architecture arch of encryption is
    signal ciphertext: integer;

begin
    process(clk)
    begin
        if(rising_edge(clk)) then
            -- Formula: (keyIn + (26 - dataIn) mod 26)
            ciphertext <= (to_integer(unsigned(keyIn)) + (26 - to_integer(unsigned(dataIn)))) mod 26;
            report "dataIn: " & integer'image(to_integer(unsigned(dataIn)));
            report "keyIn: " & integer'image(to_integer(unsigned(keyIn)));
            report "ciphertext: " & integer'image(ciphertext);
            dataOut <= std_logic_vector(to_signed(ciphertext, 8)); -- Integer to std_logic_vector
            -- Why signed and not unsigned??
        end if;
    end process;
end arch;

simulation/encryption_tb.vhd
library IEEE;
use IEEE.std_logic_1164.all;
use IEEE.numeric_std.all;

entity encryption_tb is
    --
end encryption_tb;

architecture arch of encryption_tb is
    component encryption is
        Port(
            dataIn: in std_logic_vector(7 downto 0); -- Data input (plaintext)
            keyIn: in std_logic_vector(7 downto 0); -- Key input
            dataOut: out std_logic_vector(7 downto 0); -- Data output (ciphertext)
            clk: in std_logic; -- Internal clock
            clr: in std_logic -- Clear
        );
    end component;

    constant clock_time: time := 10 ns;
    signal data_in: std_logic_vector(7 downto 0);
    signal key_in: std_logic_vector(7 downto 0);
    signal data_out: std_logic_vector(7 downto 0);
    signal clk: std_logic;
    signal clr: std_logic;

begin
    cipher: encryption port map(
        dataIn => data_in,
        keyIn => key_in,
        dataOut => data_out,
        clk => clk,
        clr => clr
    );

    clock: process
    begin
        clk <= '0';
        wait for clock_time/2;
        clk <= '1';
        wait for clock_time/2;
    end process;

    sim: process 
    begin
        clr <= '1';
        wait for clock_time;
        clr <= '0';
        wait for clock_time;

        data_in <= "01101101"; -- M
        key_in <= "01101010"; -- J
        wait for clock_time;

        data_in <= "01100001"; -- A
        key_in <= "01100101"; -- E
        wait for clock_time;
        wait;
    end process;
end arch;

simulation/wavefiles/encryption_tb.vcd
$date
  Thu Mar  5 14:17:00 2020
$end
$version
  GHDL v0
$end
$timescale
  1 fs
$end
$scope module standard $end
$upscope $end
$scope module std_logic_1164 $end
$upscope $end
$scope module numeric_std $end
$upscope $end
$scope module encryption_tb $end
$var reg 8 ! data_in[7:0] $end
$var reg 8 " key_in[7:0] $end
$var reg 8 # data_out[7:0] $end
$var reg 1 $ clk $end
$var reg 1 % clr $end
$scope module cipher $end
$var reg 8 & datain[7:0] $end
$var reg 8 ' keyin[7:0] $end
$var reg 8 ( dataout[7:0] $end
$var reg 1 ) clk $end
$var reg 1 * clr $end
$var integer 32 + ciphertext $end
$upscope $end
$upscope $end
$enddefinitions $end
#0
bUUUUUUUU !
bUUUUUUUU "
bUUUUUUUU #
0$
1%
bUUUUUUUU &
bUUUUUUUU '
bUUUUUUUU (
0)
1*
b10000000000000000000000000000000 +
#5000000
b00000000 #
1$
b00000000 (
1)
b0 +
#10000000
0$
0%
0)
0*
#15000000
1$
1)
#20000000
b01101101 !
b01101010 "
0$
b01101101 &
b01101010 '
0)
#25000000
1$
1)
b10111 +
#30000000
b01100001 !
b01100101 "
0$
b01100001 &
b01100101 '
0)
#35000000
b00010111 #
1$
b00010111 (
1)
b100 +
#40000000
b01101011 !
b01100001 "
0$
b01101011 &
b01100001 '
0)
#45000000
b00000100 #
1$
b00000100 (
1)
b10000 +
#50000000
b01100101 !
b01101110 "
0$
b01100101 &
b01101110 '
0)
#55000000
b00010000 #
1$
b00010000 (
1)
b1001 +
#60000000
0$
0)
#65000000
b00001001 #
1$
b00001001 (
1)
