key_rom.vhd
library ieee;
use ieee.std_logic_1164.all;

entity key_rom is
    Port(
        dOut: out std_logic_vector(7 downto 0);
        clk: in std_logic
    );
end key_rom;

architecture arch of key_rom is
    signal index: std_logic_vector(2 downto 0) := "000";

begin
    process(clk)
    begin
        if(rising_edge(clk)) then
            if(index = "000") then
                dOut <= "01100001"; -- a
                index <= "001";
            elsif(index = "001") then
                dOut <= "01110000"; -- p
                index <= "010";
            elsif(index = "010") then
                dOut <= "01110000"; -- p
                index <= "011";
            elsif(index = "011") then
                dOut <= "01101100"; -- l
                index <= "100";
            elsif(index = "100") then
                dOut <= "01100101"; -- e
                index <= "000";
            end if;
        end if;
    end process;
end arch;

simulation/key_rom_tb.vhd
-- Key encoder component testbench
library ieee;
use ieee.std_logic_1164.all;

entity key_rom_tb is
    --
end key_rom_tb;

architecture arch of key_rom_tb is
    component key_rom is
        Port(
            dOut: out std_logic_vector(7 downto 0);
            clk: in std_logic
        );
    end component;

    constant clock_time: time := 10 ns;
    signal data_out: std_logic_vector(7 downto 0);
    signal clk: std_logic;

begin
    key_encoder: key_rom port map(
        dOut => data_out,
        clk => clk
    );

    clock: process
    begin
        clk <= '0';
        wait for clock_time/2;
        clk <= '1';
        wait for clock_time/2;
    end process;
end arch;

simulation/wavefiles/key_rom_tb.vcd
$date
  Thu Mar  5 14:17:00 2020
$end
$version
  GHDL v0
$end
$timescale
  1 fs
$end
$scope module standard $end
$upscope $end
$scope module std_logic_1164 $end
$upscope $end
$scope module key_rom_tb $end
$var reg 8 ! data_out[7:0] $end
$var reg 1 " clk $end
$scope module key_encoder $end
$var reg 8 # dout[7:0] $end
$var reg 1 $ clk $end
$var reg 3 % index[2:0] $end
$upscope $end
$upscope $end
$enddefinitions $end
#0
bUUUUUUUU !
0"
bUUUUUUUU #
0$
b000 %
#5000000
b01100001 !
1"
b01100001 #
1$
b001 %
#10000000
0"
0$
#15000000
b01110000 !
1"
b01110000 #
1$
b010 %
#20000000
0"
0$
#25000000
1"
1$
b011 %
#30000000
0"
0$
#35000000
b01101100 !
1"
b01101100 #
1$
b100 %
#40000000
0"
0$
#45000000
b01100101 !
1"
b01100101 #
1$
b000 %
#50000000
0"
0$
#55000000
b01100001 !
1"
b01100001 #
1$
b001 %
#60000000
0"
0$
#65000000
b01110000 !
1"
b01110000 #
1$
b010 %
#70000000
0"
0$
#75000000
1"
1$
b011 %
#80000000
0"
0$
#85000000
b01101100 !
1"
b01101100 #
1$
b100 %
#90000000
0"
0$
#95000000
b01100101 !
1"
b01100101 #
1$
b000 %
