rom.vhd
-- Encoder/decoder component
library ieee;
use ieee.std_logic_1164.all;

entity rom is
    Port(
        dIn: in std_logic_vector(7 downto 0);
        dOut: out std_logic_vector(7 downto 0)
    );
end rom;

architecture arch of rom is
begin
    -- Encode from ASCII code to offset (ex. 97 -> 0)
    dOut <= "00000000" when dIn = "00000000" else -- NULL
            "00000001" when dIn = "01100001" else -- A
            "00000010" when dIn = "01100010" else -- B
            "00000011" when dIn = "01100011" else -- C
            "00000100" when dIn = "01100100" else -- D
            "00000101" when dIn = "01100101" else -- E
            "00000110" when dIn = "01100110" else -- F
            "00000111" when dIn = "01100111" else -- G
            "00001000" when dIn = "01101000" else -- H
            "00001001" when dIn = "01101001" else -- I
            "00001010" when dIn = "01101010" else -- J
            "00001011" when dIn = "01101011" else -- K
            "00001100" when dIn = "01101100" else -- L
            "00001101" when dIn = "01101101" else -- M
            "00001110" when dIn = "01101110" else -- M
            "00001111" when dIn = "01101111" else -- O
            "00010000" when dIn = "01110000" else -- P
            "00010001" when dIn = "01110001" else -- Q
            "00010010" when dIn = "01110010" else -- R
            "00010011" when dIn = "01110011" else -- S
            "00010100" when dIn = "01110100" else -- T
            "00010101" when dIn = "01110101" else -- U
            "00010110" when dIn = "01110110" else -- V
            "00010111" when dIn = "01110111" else -- W
            "00011000" when dIn = "01111000" else -- X
            "00011001" when dIn = "01111001" else -- Y
            "00011010" when dIn = "01111010" else -- Z
            
    -- Decode from offset to ASCII code (ex. 0 ->97)
            "01100001" when dIn = "00000001" else -- A
            "01100010" when dIn = "00000010" else -- B
            "01100011" when dIn = "00000011" else -- C
            "01100100" when dIn = "00000100" else -- D
            "01100101" when dIn = "00000101" else -- E
            "01100110" when dIn = "00000110" else -- F
            "01100111" when dIn = "00000111" else -- G
            "01101000" when dIn = "00001000" else -- H
            "01101001" when dIn = "00001001" else -- I
            "01101010" when dIn = "00001010" else -- J
            "01101011" when dIn = "00001011" else -- K
            "01101100" when dIn = "00001100" else -- L
            "01101101" when dIn = "00001101" else -- M
            "01101110" when dIn = "00001110" else -- M
            "01101111" when dIn = "00001111" else -- O
            "01110000" when dIn = "00010000" else -- P
            "01110001" when dIn = "00010001" else -- Q
            "01110010" when dIn = "00010010" else -- R
            "01110011" when dIn = "00010011" else -- S
            "01110100" when dIn = "00010100" else -- T
            "01110101" when dIn = "00010101" else -- U
            "01110110" when dIn = "00010110" else -- V
            "01110111" when dIn = "00010111" else -- W
            "01111000" when dIn = "00011000" else -- X
            "01111001" when dIn = "00011001" else -- Y
            "01111010" when dIn = "00011010"; -- Z
end arch;

encryption.vhd
library ieee;
use ieee.std_logic_1164.all;
use ieee.numeric_std.all;

entity encryption is
    Port(
        dataIn: in std_logic_vector(7 downto 0); -- Data input (plaintext)
        keyIn: in std_logic_vector(7 downto 0); -- Key input
        dataOut: out std_logic_vector(7 downto 0); -- Data output (ciphertext)
        clk: in std_logic; -- Internal clock
        clr: in std_logic -- Clear
    );
end encryption;

architecture arch of encryption is
    signal ciphertext: integer;

begin
    process(clk)
    begin
        -- Formula: (keyIn + (26 - dataIn) mod 26)
        ciphertext <= (to_integer(unsigned(keyIn)) + (26 - to_integer(unsigned(dataIn)))) mod 26;
        report "dataIn: " & integer'image(to_integer(unsigned(dataIn)));
        report "keyIn: " & integer'image(to_integer(unsigned(keyIn)));
        report "ciphertext: " & integer'image(ciphertext);
        dataOut <= std_logic_vector(to_signed(ciphertext, 8)); -- Integer to std_logic_vector
        -- Why signed and not unsigned??
    end process;
end arch;

top.vhd
-- Top-level implementation
library ieee;
use ieee.std_logic_1164.all;
use ieee.numeric_std.all;

entity top is
    Port(
        dataIn: in std_logic_vector(7 downto 0); -- Data input (plaintext)
        keyIn: in std_logic_vector(7 downto 0); -- Key input
        dataOut: out std_logic_vector(7 downto 0); -- Data output (ciphertext)
        clk: in std_logic; -- Internal clock
        clr: in std_logic -- Clear
    );
end top;

architecture arch of top is
    -- Encryption component
    component encryption is
        Port(
            dataIn: in std_logic_vector(7 downto 0); -- Data input (plaintext)
            keyIn: in std_logic_vector(7 downto 0); -- Key input
            dataOut: out std_logic_vector(7 downto 0); -- Data output (ciphertext)
            clk: in std_logic; -- Internal clock
            clr: in std_logic -- Clear
        );
    end component;

    -- ASCII to Binary encoder/decoder component
    component rom is
        Port(
            dIn: in std_logic_vector(7 downto 0);
            dOut: out std_logic_vector(7 downto 0)
        );
    end component;

    signal rom_to_cipher: std_logic_vector(7 downto 0);
    signal keyrom_to_cipher: std_logic_vector(7 downto 0);
    signal cipher_to_rom: std_logic_vector(7 downto 0);

begin
    data_encoder: rom port map(
        dIn => dataIn,
        dOut => rom_to_cipher
    );

    key_encoder: rom port map(
        dIn => keyIn,
        dOut => keyrom_to_cipher
    );

    cipher: encryption port map(
        dataIn => rom_to_cipher,
        keyIn => keyrom_to_cipher,
        dataOut => cipher_to_rom,
        clk => clk,
        clr => clr
    );

    decoder: rom port map(
        dIn => cipher_to_rom,
        dOut => dataOut
    );
end arch;

simulation/top_tb.vhd
-- Top-level implementation testbench
library ieee;
use ieee.std_logic_1164.all;

entity top_tb is
    --
end top_tb;

architecture arch of top_tb is
    component top is
        Port(
            dataIn: in std_logic_vector(7 downto 0); -- Data input (plaintext)
            keyIn: in std_logic_vector(7 downto 0); -- Key input
            dataOut: out std_logic_vector(7 downto 0); -- Data output (ciphertext)
            clk: in std_logic; -- Internal clock
            clr: in std_logic -- Clear
        );
    end component;

    constant clock_time: time := 10 ns;
    signal data_in: std_logic_vector(7 downto 0);
    signal key_in: std_logic_vector(7 downto 0);
    signal data_out: std_logic_vector(7 downto 0);
    signal clk: std_logic;
    signal clr: std_logic;

begin
    toplevel: top port map(
        dataIn => data_in,
        keyIn => key_in,
        dataOut => data_out,
        clk => clk,
        clr => clr
    );

    clock: process
    begin
        clk <= '0';
        wait for clock_time/2;
        clk <= '1';
        wait for clock_time/2;
    end process;

    sim: process 
    begin
        data_in <= "01101101"; -- M
        key_in <= "01101010"; -- J
        wait for clock_time;

        data_in <= "01100001"; -- A
        key_in <= "01100101"; -- E
        wait for clock_time;

        data_in <= "01101011"; -- K
        key_in <= "01100001"; -- A
        wait for clock_time;
        
        data_in <= "01100101"; -- E
        key_in <= "01101110"; -- N
        wait for clock_time;

        data_in <= "01100101"; -- E
        key_in <= "01101010"; -- J
        wait for clock_time;

        data_in <= "01110110"; -- V
        key_in <= "01100001"; -- A
        wait for clock_time;

        data_in <= "01100101"; -- E
        key_in <= "01100011"; -- C
        wait for clock_time;

        data_in <= "01110010"; -- R
        key_in <= "01110001"; -- Q
        wait for clock_time;

        data_in <= "01111001"; -- Y
        key_in <= "01110101"; -- U
        wait for clock_time;
        wait;
    end process;
end arch;

simulation/wavefiles/top_tb.vcd
$date
  Tue Mar  3 16:12:51 2020
$end
$version
  GHDL v0
$end
$timescale
  1 fs
$end
$scope module standard $end
$upscope $end
$scope module std_logic_1164 $end
$upscope $end
$scope module numeric_std $end
$upscope $end
$scope module top_tb $end
$var reg 8 ! data_in[7:0] $end
$var reg 8 " key_in[7:0] $end
$var reg 8 # data_out[7:0] $end
$var reg 1 $ clk $end
$var reg 1 % clr $end
$scope module toplevel $end
$var reg 8 & datain[7:0] $end
$var reg 8 ' keyin[7:0] $end
$var reg 8 ( dataout[7:0] $end
$var reg 1 ) clk $end
$var reg 1 * clr $end
$var reg 8 + rom_to_cipher[7:0] $end
$var reg 8 , keyrom_to_cipher[7:0] $end
$var reg 8 - cipher_to_rom[7:0] $end
$scope module data_encoder $end
$var reg 8 . din[7:0] $end
$var reg 8 / dout[7:0] $end
$upscope $end
$scope module key_encoder $end
$var reg 8 0 din[7:0] $end
$var reg 8 1 dout[7:0] $end
$upscope $end
$scope module cipher $end
$var reg 8 2 datain[7:0] $end
$var reg 8 3 keyin[7:0] $end
$var reg 8 4 dataout[7:0] $end
$var reg 1 5 clk $end
$var reg 1 6 clr $end
$var integer 32 7 ciphertext $end
$upscope $end
$scope module decoder $end
$var reg 8 8 din[7:0] $end
$var reg 8 9 dout[7:0] $end
$upscope $end
$upscope $end
$upscope $end
$enddefinitions $end
#0
b01101101 !
b01101010 "
b00000000 #
0$
U%
b01101101 &
b01101010 '
b00000000 (
0)
U*
b00001101 +
b00001010 ,
b00000000 -
b01101101 .
b00001101 /
b01101010 0
b00001010 1
b00001101 2
b00001010 3
b00000000 4
05
U6
b0 7
b00000000 8
b00000000 9
#5000000
1$
1)
15
b10111 7
#10000000
b01100001 !
b01100101 "
b01110111 #
0$
b01100001 &
b01100101 '
b01110111 (
0)
b00000001 +
b00000101 ,
b00010111 -
b01100001 .
b00000001 /
b01100101 0
b00000101 1
b00000001 2
b00000101 3
b00010111 4
05
b00010111 8
b01110111 9
#15000000
1$
1)
15
b100 7
#20000000
b01101011 !
b01100001 "
b01100100 #
0$
b01101011 &
b01100001 '
b01100100 (
0)
b00001011 +
b00000001 ,
b00000100 -
b01101011 .
b00001011 /
b01100001 0
b00000001 1
b00001011 2
b00000001 3
b00000100 4
05
b00000100 8
b01100100 9
#25000000
1$
1)
15
b10000 7
#30000000
b01100101 !
b01101110 "
b01110000 #
0$
b01100101 &
b01101110 '
b01110000 (
0)
b00000101 +
b00001110 ,
b00010000 -
b01100101 .
b00000101 /
b01101110 0
b00001110 1
b00000101 2
b00001110 3
b00010000 4
05
b00010000 8
b01110000 9
#35000000
1$
1)
15
b1001 7
#40000000
b01101010 "
b01101001 #
0$
b01101010 '
b01101001 (
0)
b00001010 ,
b00001001 -
b01101010 0
b00001010 1
b00001010 3
b00001001 4
05
b00001001 8
b01101001 9
#45000000
1$
1)
15
b101 7
#50000000
b01110110 !
b01100001 "
b01100101 #
0$
b01110110 &
b01100001 '
b01100101 (
0)
b00010110 +
b00000001 ,
b00000101 -
b01110110 .
b00010110 /
b01100001 0
b00000001 1
b00010110 2
b00000001 3
b00000101 4
05
b00000101 8
b01100101 9
#55000000
1$
1)
15
#60000000
b01100101 !
b01100011 "
0$
b01100101 &
b01100011 '
0)
b00000101 +
b00000011 ,
b01100101 .
b00000101 /
b01100011 0
b00000011 1
b00000101 2
b00000011 3
05
#65000000
1$
1)
15
b11000 7
#70000000
b01110010 !
b01110001 "
b01111000 #
0$
b01110010 &
b01110001 '
b01111000 (
0)
b00010010 +
b00010001 ,
b00011000 -
b01110010 .
b00010010 /
b01110001 0
b00010001 1
b00010010 2
b00010001 3
b00011000 4
05
b00011000 8
b01111000 9
#75000000
1$
1)
15
b11001 7
#80000000
b01111001 !
b01110101 "
b01111001 #
0$
b01111001 &
b01110101 '
b01111001 (
0)
b00011001 +
b00010101 ,
b00011001 -
b01111001 .
b00011001 /
b01110101 0
b00010101 1
b00011001 2
b00010101 3
b00011001 4
05
b00011001 8
b01111001 9
#85000000
1$
1)
15
b10110 7
#90000000
b01110110 #
0$
b01110110 (
0)
b00010110 -
b00010110 4
05
b00010110 8
b01110110 9
